wosclient/__init__.py
wosclient/cli.py
wosclient/const.py
wosclient/exceptions.py
wosclient/util.py
wosclient/wosclient.py
wosclient-0.1.5.dist-info/METADATA
wosclient-0.1.5.dist-info/RECORD
wosclient-0.1.5.dist-info/WHEEL
wosclient-0.1.5.dist-info/entry_points.txt
wosclient-0.1.5.dist-info/top_level.txt
