Metadata-Version: 2.1
Name: wosclient
Version: 0.1.5
Summary: Web of Science Article Match Retrival Client
Home-page: https://github.com/mpasternak/wosclient
Author: Michał Pasternak
Author-email: michal.dtz@gmail.com
License: MIT license
Keywords: wosclient
Platform: UNKNOWN
Classifier: Development Status :: 2 - Pre-Alpha
Classifier: Intended Audience :: Developers
Classifier: License :: OSI Approved :: MIT License
Classifier: Natural Language :: English
Classifier: Programming Language :: Python :: 3.6
Requires-Dist: Click
Requires-Dist: requests
